noughts_and_crosses/__init__.py
noughts_and_crosses/exceptions.py
noughts_and_crosses/game.py
noughts_and_crosses/play.py
noughts_and_crosses/player.py
noughts_and_crosses/position_strategy.py
noughts_and_crosses/recorder.py
noughts_and_crosses/tests/__init__.py
noughts_and_crosses/tests/test_game.py
noughts_and_crosses/tests/test_play.py
noughts_and_crosses/tests/test_position_strategy.py
noughts_and_crosses/tests/test_recorder.py
noughts_and_crosses-0.1.data/scripts/noughts_and_crosses
noughts_and_crosses-0.1.dist-info/METADATA
noughts_and_crosses-0.1.dist-info/WHEEL
noughts_and_crosses-0.1.dist-info/top_level.txt
noughts_and_crosses-0.1.dist-info/RECORD
