Metadata-Version: 2.1
Name: noughts-and-crosses
Version: 0.1
Summary: UNKNOWN
Home-page: https://github.com/andrewtmmaher/noughts-and-crosses
Author: Andrew Maher
Author-email: andrewtmmaher@gmail.com
License: UNKNOWN
Platform: UNKNOWN
Classifier: Programming Language :: Python :: 3
Classifier: License :: OSI Approved :: MIT License
Classifier: Operating System :: OS Independent
Requires-Dist: numpy
Requires-Dist: scikit-learn
Requires-Dist: scipy
